omf/__init__.py
omf/attribute.py
omf/base.py
omf/blockmodel.py
omf/composite.py
omf/fileio.py
omf/lineset.py
omf/pointset.py
omf/surface.py
omf/texture.py
omf-2.0.0a0.dist-info/METADATA
omf-2.0.0a0.dist-info/WHEEL
omf-2.0.0a0.dist-info/top_level.txt
omf-2.0.0a0.dist-info/RECORD
