Metadata-Version: 2.1
Name: omf
Version: 2.0.0a0
Summary: API Library for Open Mining Format
Home-page: https://gmggroup.org
Author: Global Mining Guidelines Group
Author-email: info@gmggroup.org
License: MIT License
Download-URL: https://github.com/gmggroup/omf
Keywords: mining data interchange
Platform: Windows
Platform: Linux
Platform: Solaris
Platform: Mac OS-X
Platform: Unix
Classifier: Development Status :: 4 - Beta
Classifier: Programming Language :: Python
Classifier: Topic :: Scientific/Engineering
Classifier: Topic :: Scientific/Engineering :: Mathematics
Classifier: Topic :: Scientific/Engineering :: Physics
Classifier: Operating System :: Microsoft :: Windows
Classifier: Operating System :: POSIX
Classifier: Operating System :: Unix
Classifier: Operating System :: MacOS
Classifier: Natural Language :: English
Requires-Dist: numpy (>=1.7)
Requires-Dist: properties (==0.6.0b0)
Requires-Dist: pypng
Requires-Dist: vectormath (>=0.2.0)
